setup.py
wsjson/__init__.py
wsjson/router.py
wsjson/server.py
wsjson.egg-info/PKG-INFO
wsjson.egg-info/SOURCES.txt
wsjson.egg-info/dependency_links.txt
wsjson.egg-info/requires.txt
wsjson.egg-info/top_level.txt