Metadata-Version: 1.0
Name: wsjson
Version: 0.6
Summary: Websocket server over Gevent wsgi server with json communication
Home-page: https://github.com/stanislavfeldman/wsjson-server
Author: Stanislav Feldman
Author-email: UNKNOWN
License: UNKNOWN
Keywords: websocket gevent json
Platform: UNKNOWN
